odoo/addons/l10n_us_base_county/README.rst
odoo/addons/l10n_us_base_county/__init__.py
odoo/addons/l10n_us_base_county/__manifest__.py
odoo/addons/l10n_us_base_county/data/res.country.state.county.csv
odoo/addons/l10n_us_base_county/i18n/l10n_us_base_county.pot
odoo/addons/l10n_us_base_county/models/__init__.py
odoo/addons/l10n_us_base_county/models/res_country_state_county.py
odoo/addons/l10n_us_base_county/models/res_partner.py
odoo/addons/l10n_us_base_county/readme/CONTRIBUTORS.md
odoo/addons/l10n_us_base_county/readme/DESCRIPTION.md
odoo/addons/l10n_us_base_county/security/ir.model.access.csv
odoo/addons/l10n_us_base_county/static/description/icon.png
odoo/addons/l10n_us_base_county/static/description/index.html
odoo/addons/l10n_us_base_county/tests/__init__.py
odoo/addons/l10n_us_base_county/tests/test_res_country_state_county.py
odoo/addons/l10n_us_base_county/tests/data/LND01.csv
odoo/addons/l10n_us_base_county/views/res_country_state_county_views.xml
odoo/addons/l10n_us_base_county/views/res_partner_views.xml
odoo_addon_l10n_us_base_county-18.0.0.0.0.2.dist-info/METADATA
odoo_addon_l10n_us_base_county-18.0.0.0.0.2.dist-info/WHEEL
odoo_addon_l10n_us_base_county-18.0.0.0.0.2.dist-info/top_level.txt
odoo_addon_l10n_us_base_county-18.0.0.0.0.2.dist-info/RECORD
